mklib_services/__about__.py
mklib_services/__init__.py
mklib_services/__main__.py
mklib_services/data.py
mklib_services/excel.py
mklib_services/rows.py
mklib_services/tempCodeRunnerFile.py
madskris_mklib_services-0.0.1.dist-info/METADATA
madskris_mklib_services-0.0.1.dist-info/WHEEL
madskris_mklib_services-0.0.1.dist-info/licenses/LICENSE.txt
madskris_mklib_services-0.0.1.dist-info/RECORD
